[
  {
    "ContainingType": "WebApplication1.Controllers.ManagerController",
    "Method": "AddManager",
    "RelativePath": "api/Manager/AddManager",
    "HttpMethod": "POST",
    "IsController": true,
    "Order": 0,
    "Parameters": [
      {
        "Name": "managerModel",
        "Type": "WebApplication1.DTO.ManagerDTO",
        "IsRequired": true
      }
    ],
    "ReturnTypes": [
      {
        "Type": "WebApplication1.DTO.ManagerDTO",
        "MediaTypes": [
          "text/plain",
          "application/json",
          "text/json"
        ],
        "StatusCode": 200
      }
    ]
  },
  {
    "ContainingType": "WebApplication1.Controllers.ManagerController",
    "Method": "AddOfficeUser",
    "RelativePath": "api/Manager/AddOfficeUser",
    "HttpMethod": "POST",
    "IsController": true,
    "Order": 0,
    "Parameters": [
      {
        "Name": "officeModel",
        "Type": "WebApplication1.DTO.OfficeDTO",
        "IsRequired": true
      }
    ],
    "ReturnTypes": []
  },
  {
    "ContainingType": "WebApplication1.Controllers.ManagerController",
    "Method": "AddSecurityUser",
    "RelativePath": "api/Manager/AddSecurityUser",
    "HttpMethod": "POST",
    "IsController": true,
    "Order": 0,
    "Parameters": [
      {
        "Name": "securityModel",
        "Type": "WebApplication1.DTO.SecurityDTO",
        "IsRequired": true
      }
    ],
    "ReturnTypes": []
  },
  {
    "ContainingType": "WebApplication1.Controllers.ManagerController",
    "Method": "DeleteSecurity",
    "RelativePath": "api/Manager/DeleteSecurity/{id}",
    "HttpMethod": "DELETE",
    "IsController": true,
    "Order": 0,
    "Parameters": [
      {
        "Name": "id",
        "Type": "System.String",
        "IsRequired": true
      }
    ],
    "ReturnTypes": []
  },
  {
    "ContainingType": "WebApplication1.Controllers.ManagerController",
    "Method": "GetManagerById",
    "RelativePath": "api/Manager/GetManagerById/{id}",
    "HttpMethod": "GET",
    "IsController": true,
    "Order": 0,
    "Parameters": [
      {
        "Name": "id",
        "Type": "System.String",
        "IsRequired": true
      }
    ],
    "ReturnTypes": [
      {
        "Type": "WebApplication1.DTO.ManagerDTO",
        "MediaTypes": [
          "text/plain",
          "application/json",
          "text/json"
        ],
        "StatusCode": 200
      }
    ]
  },
  {
    "ContainingType": "WebApplication1.Controllers.ManagerController",
    "Method": "GetVisitorsByStatus",
    "RelativePath": "api/Manager/GetVisitorsByStatus/{status}",
    "HttpMethod": "GET",
    "IsController": true,
    "Order": 0,
    "Parameters": [
      {
        "Name": "status",
        "Type": "System.Boolean",
        "IsRequired": true
      }
    ],
    "ReturnTypes": []
  },
  {
    "ContainingType": "WebApplication1.Controllers.ManagerController",
    "Method": "UpdateManager",
    "RelativePath": "api/Manager/UpdateManager/{id}",
    "HttpMethod": "PUT",
    "IsController": true,
    "Order": 0,
    "Parameters": [
      {
        "Name": "id",
        "Type": "System.String",
        "IsRequired": true
      },
      {
        "Name": "managerModel",
        "Type": "WebApplication1.DTO.ManagerDTO",
        "IsRequired": true
      }
    ],
    "ReturnTypes": []
  },
  {
    "ContainingType": "WebApplication1.Controllers.ManagerController",
    "Method": "UpdateVisitorStatus",
    "RelativePath": "api/Manager/UpdateVisitorStatus/{visitorId}",
    "HttpMethod": "PUT",
    "IsController": true,
    "Order": 0,
    "Parameters": [
      {
        "Name": "visitorId",
        "Type": "System.String",
        "IsRequired": true
      },
      {
        "Name": "newStatus",
        "Type": "System.Boolean",
        "IsRequired": false
      }
    ],
    "ReturnTypes": []
  },
  {
    "ContainingType": "WebApplication1.Controllers.OfficeUserController",
    "Method": "AddOffice",
    "RelativePath": "api/OfficeUser/AddOffice",
    "HttpMethod": "POST",
    "IsController": true,
    "Order": 0,
    "Parameters": [
      {
        "Name": "officeModel",
        "Type": "WebApplication1.DTO.OfficeDTO",
        "IsRequired": true
      }
    ],
    "ReturnTypes": [
      {
        "Type": "WebApplication1.DTO.OfficeDTO",
        "MediaTypes": [
          "text/plain",
          "application/json",
          "text/json"
        ],
        "StatusCode": 200
      }
    ]
  },
  {
    "ContainingType": "WebApplication1.Controllers.OfficeUserController",
    "Method": "DeleteOffice",
    "RelativePath": "api/OfficeUser/DeleteOffice/{id}",
    "HttpMethod": "DELETE",
    "IsController": true,
    "Order": 0,
    "Parameters": [
      {
        "Name": "id",
        "Type": "System.String",
        "IsRequired": true
      }
    ],
    "ReturnTypes": []
  },
  {
    "ContainingType": "WebApplication1.Controllers.OfficeUserController",
    "Method": "GetOfficeById",
    "RelativePath": "api/OfficeUser/GetOfficeById/{id}",
    "HttpMethod": "GET",
    "IsController": true,
    "Order": 0,
    "Parameters": [
      {
        "Name": "id",
        "Type": "System.String",
        "IsRequired": true
      }
    ],
    "ReturnTypes": [
      {
        "Type": "WebApplication1.DTO.OfficeDTO",
        "MediaTypes": [
          "text/plain",
          "application/json",
          "text/json"
        ],
        "StatusCode": 200
      }
    ]
  },
  {
    "ContainingType": "WebApplication1.Controllers.OfficeUserController",
    "Method": "GetVisitorsByStatus",
    "RelativePath": "api/OfficeUser/GetVisitorsByStatus/{status}",
    "HttpMethod": "GET",
    "IsController": true,
    "Order": 0,
    "Parameters": [
      {
        "Name": "status",
        "Type": "System.Boolean",
        "IsRequired": true
      }
    ],
    "ReturnTypes": []
  },
  {
    "ContainingType": "WebApplication1.Controllers.OfficeUserController",
    "Method": "Login",
    "RelativePath": "api/OfficeUser/Login",
    "HttpMethod": "POST",
    "IsController": true,
    "Order": 0,
    "Parameters": [
      {
        "Name": "loginModel",
        "Type": "WebApplication1.DTO.LoginDTO",
        "IsRequired": true
      }
    ],
    "ReturnTypes": []
  },
  {
    "ContainingType": "WebApplication1.Controllers.OfficeUserController",
    "Method": "UpdateOffice",
    "RelativePath": "api/OfficeUser/UpdateOffice/{id}",
    "HttpMethod": "PUT",
    "IsController": true,
    "Order": 0,
    "Parameters": [
      {
        "Name": "id",
        "Type": "System.String",
        "IsRequired": true
      },
      {
        "Name": "securityModel",
        "Type": "WebApplication1.DTO.OfficeDTO",
        "IsRequired": true
      }
    ],
    "ReturnTypes": []
  },
  {
    "ContainingType": "WebApplication1.Controllers.OfficeUserController",
    "Method": "UpdateVisitorStatus",
    "RelativePath": "api/OfficeUser/UpdateVisitorStatus/{visitorId}",
    "HttpMethod": "PUT",
    "IsController": true,
    "Order": 0,
    "Parameters": [
      {
        "Name": "visitorId",
        "Type": "System.String",
        "IsRequired": true
      },
      {
        "Name": "newStatus",
        "Type": "System.Boolean",
        "IsRequired": false
      }
    ],
    "ReturnTypes": []
  },
  {
    "ContainingType": "WebApplication1.Controllers.SecurityUserController",
    "Method": "DeleteSecurity",
    "RelativePath": "api/SecurityUser/DeleteSecurity/{id}",
    "HttpMethod": "DELETE",
    "IsController": true,
    "Order": 0,
    "Parameters": [
      {
        "Name": "id",
        "Type": "System.String",
        "IsRequired": true
      }
    ],
    "ReturnTypes": []
  },
  {
    "ContainingType": "WebApplication1.Controllers.SecurityUserController",
    "Method": "GetSecurityById",
    "RelativePath": "api/SecurityUser/GetSecurityById/{id}",
    "HttpMethod": "GET",
    "IsController": true,
    "Order": 0,
    "Parameters": [
      {
        "Name": "id",
        "Type": "System.String",
        "IsRequired": true
      }
    ],
    "ReturnTypes": [
      {
        "Type": "WebApplication1.DTO.SecurityDTO",
        "MediaTypes": [
          "text/plain",
          "application/json",
          "text/json"
        ],
        "StatusCode": 200
      }
    ]
  },
  {
    "ContainingType": "WebApplication1.Controllers.SecurityUserController",
    "Method": "GetVisitorById",
    "RelativePath": "api/SecurityUser/GetVisitorById/{id}",
    "HttpMethod": "GET",
    "IsController": true,
    "Order": 0,
    "Parameters": [
      {
        "Name": "id",
        "Type": "System.String",
        "IsRequired": true
      }
    ],
    "ReturnTypes": [
      {
        "Type": "WebApplication1.DTO.VisitorDTO",
        "MediaTypes": [
          "text/plain",
          "application/json",
          "text/json"
        ],
        "StatusCode": 200
      }
    ]
  },
  {
    "ContainingType": "WebApplication1.Controllers.SecurityUserController",
    "Method": "GetVisitorsByStatus",
    "RelativePath": "api/SecurityUser/GetVisitorsByStatus/{status}",
    "HttpMethod": "GET",
    "IsController": true,
    "Order": 0,
    "Parameters": [
      {
        "Name": "status",
        "Type": "System.Boolean",
        "IsRequired": true
      }
    ],
    "ReturnTypes": []
  },
  {
    "ContainingType": "WebApplication1.Controllers.SecurityUserController",
    "Method": "Login",
    "RelativePath": "api/SecurityUser/Login",
    "HttpMethod": "POST",
    "IsController": true,
    "Order": 0,
    "Parameters": [
      {
        "Name": "loginModel",
        "Type": "WebApplication1.DTO.LoginDTO",
        "IsRequired": true
      }
    ],
    "ReturnTypes": []
  },
  {
    "ContainingType": "WebApplication1.Controllers.SecurityUserController",
    "Method": "UpdateSecurity",
    "RelativePath": "api/SecurityUser/UpdateSecurity/{id}",
    "HttpMethod": "PUT",
    "IsController": true,
    "Order": 0,
    "Parameters": [
      {
        "Name": "id",
        "Type": "System.String",
        "IsRequired": true
      },
      {
        "Name": "securityModel",
        "Type": "WebApplication1.DTO.SecurityDTO",
        "IsRequired": true
      }
    ],
    "ReturnTypes": []
  },
  {
    "ContainingType": "WebApplication1.Controllers.VisitorController",
    "Method": "AddVisitor",
    "RelativePath": "api/Visitor/AddVisitor",
    "HttpMethod": "POST",
    "IsController": true,
    "Order": 0,
    "Parameters": [
      {
        "Name": "visitoModel",
        "Type": "WebApplication1.DTO.VisitorDTO",
        "IsRequired": true
      }
    ],
    "ReturnTypes": [
      {
        "Type": "WebApplication1.DTO.VisitorDTO",
        "MediaTypes": [
          "text/plain",
          "application/json",
          "text/json"
        ],
        "StatusCode": 200
      }
    ]
  },
  {
    "ContainingType": "WebApplication1.Controllers.VisitorController",
    "Method": "DeleteVisitor",
    "RelativePath": "api/Visitor/DeleteVisitor",
    "HttpMethod": "DELETE",
    "IsController": true,
    "Order": 0,
    "Parameters": [
      {
        "Name": "id",
        "Type": "System.String",
        "IsRequired": false
      }
    ],
    "ReturnTypes": []
  },
  {
    "ContainingType": "WebApplication1.Controllers.VisitorController",
    "Method": "GetAllVisitors",
    "RelativePath": "api/Visitor/GetAllVisitors",
    "HttpMethod": "GET",
    "IsController": true,
    "Order": 0,
    "Parameters": [],
    "ReturnTypes": [
      {
        "Type": "System.Collections.Generic.IEnumerable\u00601[[WebApplication1.DTO.VisitorDTO, WebApplication1, Version=1.0.0.0, Culture=neutral, PublicKeyToken=null]]",
        "MediaTypes": [
          "text/plain",
          "application/json",
          "text/json"
        ],
        "StatusCode": 200
      }
    ]
  },
  {
    "ContainingType": "WebApplication1.Controllers.VisitorController",
    "Method": "GetVisitorById",
    "RelativePath": "api/Visitor/GetVisitorById/{id}",
    "HttpMethod": "GET",
    "IsController": true,
    "Order": 0,
    "Parameters": [
      {
        "Name": "id",
        "Type": "System.String",
        "IsRequired": true
      }
    ],
    "ReturnTypes": [
      {
        "Type": "WebApplication1.DTO.VisitorDTO",
        "MediaTypes": [
          "text/plain",
          "application/json",
          "text/json"
        ],
        "StatusCode": 200
      }
    ]
  },
  {
    "ContainingType": "WebApplication1.Controllers.VisitorController",
    "Method": "UpdateVisitor",
    "RelativePath": "api/Visitor/UpdateVisitor",
    "HttpMethod": "PUT",
    "IsController": true,
    "Order": 0,
    "Parameters": [
      {
        "Name": "id",
        "Type": "System.String",
        "IsRequired": false
      },
      {
        "Name": "visitorModel",
        "Type": "WebApplication1.DTO.VisitorDTO",
        "IsRequired": true
      }
    ],
    "ReturnTypes": []
  }
]